{"Epoch0": {"train_loss_means": 0.5629613995552063, "val_loss_mean": 0.5120953321456909, "val_f1_majority_bin": 0.0, "val_f1_majority_macro": 0.49565689467969604, "val_acc_majority": 0.9827771782875061, "val_f1_individual_binary": 0.0, "val_f1_individual_macro": 0.49649415692821375, "val_acc_individual": 0.9860742688179016, "train_acc_means": 0.9814285635948181, "train_time_millis": 10535.198784898967, "eval_time_millis": 1527.3090922273695}, "Epoch1": {"train_loss_means": 0.4920485019683838, "val_loss_mean": 0.5358725786209106, "val_f1_majority_bin": 0.0, "val_f1_majority_macro": 0.49565689467969604, "val_acc_majority": 0.9827771782875061, "val_f1_individual_binary": 0.0, "val_f1_individual_macro": 0.49649415692821375, "val_acc_individual": 0.9860742688179016, "train_acc_means": 0.9814285635948181, "train_time_millis": 10551.193410065025, "eval_time_millis": 1524.021991994232}, "Epoch2": {"train_loss_means": 0.4140661060810089, "val_loss_mean": 0.5739914178848267, "val_f1_majority_bin": 0.0, "val_f1_majority_macro": 0.49538294405214556, "val_acc_majority": 0.9817007780075073, "val_f1_individual_binary": 0.0, "val_f1_individual_macro": 0.49598930481283426, "val_acc_individual": 0.9840849041938782, "train_acc_means": 0.9807142615318298, "train_time_millis": 10627.44245911017, "eval_time_millis": 1526.2050316669047}, "Test_results": {"test_f1_majority_binary": 0.0, "test_f1_majority_macro": 0.49475524475524474, "test_acc_majority": 0.979238748550415, "test_f1_individual_binary": 0.0, "test_f1_individual_macro": 0.49599999999999994, "test_acc_individual": 0.9841269850730896, "test_time_millis": 1418.6227298341691, "dataset_size": 4589, "number_of_annotations": 4589}}